mtkahypar.cpython-311-aarch64-linux-gnu.so
mtkahypar.libs/libhwloc-8ede5728.so.15.2.0
mtkahypar.libs/libtbb-85e63ba4.so.12.14
mtkahypar.libs/libtbbmalloc-0ed4d9f8.so.2.14
mtkahypar-1.5.3.dist-info/METADATA
mtkahypar-1.5.3.dist-info/WHEEL
mtkahypar-1.5.3.dist-info/RECORD
mtkahypar-1.5.3.dist-info/licenses/LICENSE
