Metadata-Version: 2.1
Name: mtkahypar
Version: 1.5.3
Summary: Mt-KaHyPar: Multi-Threaded Karlsruhe Hypergraph Partitioning
Author-Email: Mt-KaHyPar Developers <mtkahypar-devs@mail.informatik.kit.edu>
License: MIT License
Classifier: Development Status :: 5 - Production/Stable
Classifier: Topic :: Scientific/Engineering
Classifier: Topic :: Software Development :: Libraries :: Python Modules
Classifier: License :: OSI Approved :: MIT License
Project-URL: github, https://github.com/kahypar/mt-kahypar
Requires-Python: >=3.7
